{
  "timestamp": "2025-09-04T14:25:41.856Z",
  "testUser": {
    "email": "test.211b2d124537aa8f@example.com"
  },
  "userStatusWorking": true,
  "dashboardWorking": true,
  "endpointResults": [
    {
      "endpoint": "GET /api/health",
      "status": 200,
      "success": true,
      "requiresAuth": false
    },
    {
      "endpoint": "GET /api/auth/verify",
      "status": 200,
      "success": true,
      "requiresAuth": true
    },
    {
      "endpoint": "GET /api/user/status",
      "status": 200,
      "success": true,
      "requiresAuth": true
    },
    {
      "endpoint": "GET /api/dashboard",
      "status": 200,
      "success": true,
      "requiresAuth": true
    },
    {
      "endpoint": "GET /api/user/profile",
      "status": 404,
      "success": false,
      "requiresAuth": true
    },
    {
      "endpoint": "GET /api/workflows",
      "status": 200,
      "success": true,
      "requiresAuth": true
    },
    {
      "endpoint": "GET /api/analytics",
      "status": 200,
      "success": true,
      "requiresAuth": true
    }
  ],
  "summary": {
    "workingEndpoints": 6,
    "totalEndpoints": 7,
    "successRate": 86
  }
}